{"ygPerms":{"resourceCapabilityList":[{"resourceType":"GROUP","capabilities":[{"name":"READ"},{"name":"JOIN"}]},{"resourceType":"PHOTO","capabilities":[]},{"resourceType":"FILE","capabilities":[]},{"resourceType":"MEMBER","capabilities":[]},{"resourceType":"LINK","capabilities":[]},{"resourceType":"CALENDAR","capabilities":[]},{"resourceType":"DATABASE","capabilities":[]},{"resourceType":"POLL","capabilities":[]},{"resourceType":"MESSAGE","capabilities":[{"name":"READ"}]},{"resourceType":"PENDING_MESSAGE","capabilities":[]},{"resourceType":"ATTACHMENTS","capabilities":[{"name":"READ"}]},{"resourceType":"PHOTOMATIC_ALBUMS","capabilities":[]},{"resourceType":"MEMBERSHIP_TYPE","capabilities":[]},{"resourceType":"POST","capabilities":[{"name":"READ"}]},{"resourceType":"PIN","capabilities":[]}],"groupUrl":"groups.yahoo.com","intlCode":"us"},"comscore":"pageview_candidate","ygData":{"userId":344770313,"authorName":"Colin Green","from":"Colin Green &lt;colin.green1@...&gt;","profile":"alienseedpod","replyTo":"LIST","senderId":"dNzaI45TW6qZNT6gZKwIkt60yMk0yax-UHFTTe3ahRdMUmeSupLUknXkSzNlHDLV1rKEgurPMQVW977H4v-a9S5Pdi7w8g6KhysbXnu4Kck","spamInfo":{"isSpam":false,"reason":"12"},"subject":"Re: [neat] Reminder: Mario AI Competition 2009","postDate":"1249473284","msgId":4804,"canDelete":false,"contentTrasformed":false,"systemMessage":false,"headers":{"messageIdInHeader":"PDcyN2E0MDZjMDkwODA1MDQ1NHY1OGRhMWNkYWg5MDY3ODljN2QyY2E4NDY1QG1haWwuZ21haWwuY29tPg==","inReplyToHeader":"PDIzMGU0NjNlMDkwODA0MDI0NXYyMDUzMWU5M2c4Mjc0MjFmMGFlN2E4MzRkQG1haWwuZ21haWwuY29tPg==","referencesHeader":"PDIzMGU0NjNlMDkwODA0MDI0NXYyMDUzMWU5M2c4Mjc0MjFmMGFlN2E4MzRkQG1haWwuZ21haWwuY29tPg=="},"prevInTopic":4801,"nextInTopic":0,"prevInTime":4803,"nextInTime":4805,"topicId":4801,"numMessagesInTopic":2,"msgSnippet":"Congrats on getting to the front page of slashdot :)","rawEmail":"Return-Path: &lt;colin.green1@...&gt;\r\nX-Sender: colin.green1@...\r\nX-Apparently-To: neat@yahoogroups.com\r\nX-Received: (qmail 91573 invoked from network); 5 Aug 2009 11:54:45 -0000\r\nX-Received: from unknown (98.137.34.44)\n  by m4.grp.re1.yahoo.com with QMQP; 5 Aug 2009 11:54:45 -0000\r\nX-Received: from unknown (HELO mail-yw0-f188.google.com) (209.85.211.188)\n  by mta1.grp.sp2.yahoo.com with SMTP; 5 Aug 2009 11:54:45 -0000\r\nX-Received: by mail-yw0-f188.google.com with SMTP id 26so43802ywh.5\n        for &lt;neat@yahoogroups.com&gt;; Wed, 05 Aug 2009 04:54:45 -0700 (PDT)\r\nMIME-Version: 1.0\r\nX-Received: by 10.90.32.9 with SMTP id f9mr3841132agf.103.1249473284923; Wed, 05 \n\tAug 2009 04:54:44 -0700 (PDT)\r\nIn-Reply-To: &lt;230e463e0908040245v20531e93g827421f0ae7a834d@...&gt;\r\nReferences: &lt;230e463e0908040245v20531e93g827421f0ae7a834d@...&gt;\r\nDate: Wed, 5 Aug 2009 12:54:44 +0100\r\nMessage-ID: &lt;727a406c0908050454v58da1cdah906789c7d2ca8465@...&gt;\r\nTo: neat@yahoogroups.com\r\nContent-Type: text/plain; charset=ISO-8859-1\r\nContent-Transfer-Encoding: 7bit\r\nX-eGroups-Msg-Info: 1:12:0:0:0\r\nFrom: Colin Green &lt;colin.green1@...&gt;\r\nSubject: Re: [neat] Reminder: Mario AI Competition 2009\r\nX-Yahoo-Group-Post: member; u=344770313; y=h_JyqZaelordFrmrBBIs7y2aZbvmdyjUJ4HDmG3Rpc_dIZaAp8NF\r\nX-Yahoo-Profile: alienseedpod\r\n\r\nCongrats on getting to the front page of slashdot :)\n\n"}}