{"ygPerms":{"resourceCapabilityList":[{"resourceType":"GROUP","capabilities":[{"name":"READ"},{"name":"JOIN"}]},{"resourceType":"PHOTO","capabilities":[]},{"resourceType":"FILE","capabilities":[]},{"resourceType":"MEMBER","capabilities":[]},{"resourceType":"LINK","capabilities":[]},{"resourceType":"CALENDAR","capabilities":[]},{"resourceType":"DATABASE","capabilities":[]},{"resourceType":"POLL","capabilities":[]},{"resourceType":"MESSAGE","capabilities":[{"name":"READ"}]},{"resourceType":"PENDING_MESSAGE","capabilities":[]},{"resourceType":"ATTACHMENTS","capabilities":[{"name":"READ"}]},{"resourceType":"PHOTOMATIC_ALBUMS","capabilities":[]},{"resourceType":"MEMBERSHIP_TYPE","capabilities":[]},{"resourceType":"POST","capabilities":[{"name":"READ"}]},{"resourceType":"PIN","capabilities":[]}],"groupUrl":"groups.yahoo.com","intlCode":"us"},"comscore":"pageview_candidate","ygData":{"userId":298998173,"authorName":"Jeff Haynes","from":"Jeff Haynes &lt;feedyurhed@...&gt;","profile":"jefffhaynes","replyTo":"LIST","senderId":"1welKunNTJKFwI6ZUBKiqgkrKyNpfrK6G542w08ZJR-n-MWdeopp45ed7_ZJL4ah83kVEKX1q-pfy6p_wRQuo6e_5Zk6g2A_Hg","spamInfo":{"isSpam":false,"reason":"12"},"subject":"Re: [neat] Biology-like Learning","postDate":"1259478474","msgId":4939,"canDelete":false,"contentTrasformed":false,"systemMessage":false,"headers":{"messageIdInHeader":"PDkzNzc4NGMwMDkxMTI4MjMwN241ZmIwOTAyMms1MzU2NzQwZTM2YmJhNzgxQG1haWwuZ21haWwuY29tPg==","inReplyToHeader":"PDU5NDhmMTA5MDkxMTI4MjIyNmwzOTA3MDQzNnFlMzI2ODdkYmYwZTY5M2NiQG1haWwuZ21haWwuY29tPg==","referencesHeader":"PDU5NDhmMTA5MDkxMTI4MjIyNmwzOTA3MDQzNnFlMzI2ODdkYmYwZTY5M2NiQG1haWwuZ21haWwuY29tPg=="},"prevInTopic":4938,"nextInTopic":4940,"prevInTime":4938,"nextInTime":4940,"topicId":4938,"numMessagesInTopic":4,"msgSnippet":"I think you failed to grasp what David was saying.  Evolution is not a learning algorithm in the traditional sense.  However, it is how the topography of the","rawEmail":"Return-Path: &lt;feedyurhed@...&gt;\r\nX-Sender: feedyurhed@...\r\nX-Apparently-To: neat@yahoogroups.com\r\nX-Received: (qmail 46769 invoked from network); 29 Nov 2009 07:07:56 -0000\r\nX-Received: from unknown (98.137.34.44)\n  by m1.grp.sp2.yahoo.com with QMQP; 29 Nov 2009 07:07:56 -0000\r\nX-Received: from unknown (HELO fg-out-1718.google.com) (72.14.220.155)\n  by mta1.grp.sp2.yahoo.com with SMTP; 29 Nov 2009 07:07:55 -0000\r\nX-Received: by fg-out-1718.google.com with SMTP id l26so563925fgb.0\n        for &lt;neat@yahoogroups.com&gt;; Sat, 28 Nov 2009 23:07:54 -0800 (PST)\r\nMIME-Version: 1.0\r\nX-Received: by 10.103.84.25 with SMTP id m25mr999942mul.111.1259478474451; Sat, \n\t28 Nov 2009 23:07:54 -0800 (PST)\r\nIn-Reply-To: &lt;5948f1090911282226l39070436qe32687dbf0e693cb@...&gt;\r\nReferences: &lt;5948f1090911282226l39070436qe32687dbf0e693cb@...&gt;\r\nDate: Sun, 29 Nov 2009 02:07:54 -0500\r\nMessage-ID: &lt;937784c00911282307n5fb09022k5356740e36bba781@...&gt;\r\nTo: neat@yahoogroups.com\r\nContent-Type: multipart/alternative; boundary=0016e652f6b0126d6004797d2f8b\r\nX-eGroups-Msg-Info: 1:12:0:0:0\r\nFrom: Jeff Haynes &lt;feedyurhed@...&gt;\r\nSubject: Re: [neat] Biology-like Learning\r\nX-Yahoo-Group-Post: member; u=298998173; y=Q3NWFRLYQzVEjusXw4wb-SEGFItwSZ0ODMnZ29VRdvYBo6DNzrk\r\nX-Yahoo-Profile: jefffhaynes\r\n\r\n\r\n--0016e652f6b0126d6004797d2f8b\r\nContent-Type: text/plain; charset=windows-1252\r\nContent-Transfer-Encoding: quoted-printable\r\n\r\nI think you failed to grasp what David was saying.  Evolution is not a\nlear=\r\nning algorithm in the traditional sense.  However, it is how the\ntopography=\r\n of the brain was created in the first place.  If you&#39;re looking\nsimply for=\r\n learning algorithms I suggest you look into any of a great number\nof resou=\r\nrces available for training neural networks.  As David pointed out,\nmuch of=\r\n the work to date represents a radical simplification of biological\nsystems=\r\n.  If you&#39;re looking for something that closely mimics biology you\nmight lo=\r\nok at work that has been done in modeling a single neuron.  That&#39;s\nprobably=\r\n almost as good as it gets for the time being.\n\n- Jeff\n\n\nOn Sun, Nov 29, 20=\r\n09 at 1:26 AM, Richard Gong &lt;gongrichard@...&gt; wrote:\n\n&gt;\n&gt;\n&gt; Evolution=\r\n is not how biological neural networks learn. Are there any\n&gt; projects (sim=\r\nilar in scope/usability to NEAT) that are more faithful to\n&gt; biology?\n&gt;\n&gt; R=\r\nichard Gong\n&gt;\n&gt;\n&gt; ---------- Forwarded message ----------\n&gt; From: Dave Tour=\r\netzky &lt;dst@...&gt;\n&gt; Date: Sat, Nov 28, 2009 at 1:59 AM\n&gt; S=\r\nubject: Re: AI\n&gt; To: Richard Gong &lt;richardgong@...&gt;\n&gt;\n&gt;\n&gt; &gt; Are there=\r\n any coding projects similar to NEAT, in its generalized\n&gt; &gt; ability, but m=\r\nore like the brain&#39;s &quot;live&quot; learning?\n&gt;\n&gt; No one knows in detail how learni=\r\nng works in the brain.  We don&#39;t know\n&gt; how most things are represented, or=\r\n how those representations get\n&gt; updated.  All we have right now are highly=\r\n simplified models at various\n&gt; levels of abstraction, but we know that the=\r\nse are inadequate.\n&gt;\n&gt; Don&#39;t be misled by computer scientists who give simp=\r\nle learning\n&gt; mechanisms fancy biological names, like &quot;neural network&quot; or &quot;=\r\ngenetic\n&gt; algorithm&quot;.  These are highly simplified and abstract mathematica=\r\nl\n&gt; constructs compared to the complicated and messy biological phenomena\n&gt;=\r\n they are named after.  It&#39;s like the difference between the hypothetical\n&gt;=\r\n canonball&#39;s simple 1D trajectory in a vacuum, vs. a real world\n&gt; knuckleba=\r\nll whose spin and trajectory can only be explained using vector\n&gt; calculus =\r\nand fluid dynamics.\n&gt;\n&gt; So to answer your original question: no, we don&#39;t h=\r\nave a general purpose\n&gt; learning rule that works like the brain, because we=\r\n don&#39;t understand how\n&gt; the brain works.\n&gt;\n&gt; And although brains have very =\r\npowerful learning algorithms, they also\n&gt; have a lot of built-in structure =\r\nthat is present from birth.  Most\n&gt; machine learning algorithms start out w=\r\nith zero weights, or initial\n&gt; random weights, not the incredibly detailed =\r\nstructure produced by our\n&gt; genes through the process of fetal development.=\r\n  So don&#39;t think that\n&gt; some simple learning algorithm is going to provide =\r\nthe &quot;magic bullet&quot;\n&gt; that produces intelligent machines.  It&#39;s not going to=\r\n be that easy.  It\n&gt; took evolution a long time to come up with the structu=\r\nre of the\n&gt; mammalian brain.  And it&#39;s going to take us another century or =\r\ntwo to\n&gt; figure out how it works.\n&gt;\n&gt; -- Dr. David S. Touretzky\n&gt;   Researc=\r\nh Professor\n&gt;   Computer Science Department &\n&gt;     Center for the Neural B=\r\nasis of Cognition\n&gt;   Carnegie Mellon University\n&gt;   Pittsburgh, PA 15213-3=\r\n891\n&gt;   tel. 412-268-7561\n&gt;\n&gt;  \n&gt;\n\n\n\n-- \n...imagine a puddle waking up one =\r\nmorning and thinking, &#39;This is an\ninteresting world I find myself in, an in=\r\nteresting hole I find myself in,\nfits me rather neatly, doesn&#39;t it? In fact=\r\n it fits me staggeringly well,\nmust have been made to have me in it!&#39; This =\r\nis such a powerful idea that as\nthe sun rises in the sky and the air heats =\r\nup and as, gradually, the puddle\ngets smaller and smaller, it&#39;s still frant=\r\nically hanging on to the notion\nthat everything&#39;s going to be alright, beca=\r\nuse this world was meant to have\nhim in it, was built to have him in it; so=\r\n the moment he disappears catches\nhim rather by surprise. I think this may =\r\nbe something we need to be on the\nwatch out for.\n\n-- Douglas Adams\n\r\n--0016e652f6b0126d6004797d2f8b\r\nContent-Type: text/html; charset=windows-1252\r\nContent-Transfer-Encoding: quoted-printable\r\n\r\nI think you failed to grasp what David was saying. =A0Evolution is not a le=\r\narning algorithm in the traditional sense. =A0However, it is how the topogr=\r\naphy of the brain was created in the first place. =A0If you&#39;re looking =\r\nsimply for learning algorithms I suggest you look into any of a great numbe=\r\nr of resources available for training neural networks. =A0As David pointed =\r\nout, much of the work to date represents a radical simplification of biolog=\r\nical systems. =A0If you&#39;re looking for something that closely mimics bi=\r\nology you might look at work that has been done in modeling a single neuron=\r\n. =A0That&#39;s probably almost as good as it gets for the time being.&lt;div&gt;=\r\n\n&lt;br&gt;&lt;/div&gt;&lt;div&gt;- Jeff&lt;/div&gt;&lt;div&gt;&lt;br&gt;&lt;br&gt;&lt;div class=3D&quot;gmail_quote&quot;&gt;On Sun,=\r\n Nov 29, 2009 at 1:26 AM, Richard Gong &lt;span dir=3D&quot;ltr&quot;&gt;&lt;&lt;a href=3D&quot;mai=\r\nlto:gongrichard@...&quot;&gt;gongrichard@...&lt;/a&gt;&gt;&lt;/span&gt; wrote:&lt;br&gt;&lt;=\r\nblockquote class=3D&quot;gmail_quote&quot; style=3D&quot;margin:0 0 0 .8ex;border-left:1px=\r\n #ccc solid;padding-left:1ex;&quot;&gt;\n\n\n\n\n\n\n\n\n\n\n\n\n\n\n&lt;div style=3D&quot;background-colo=\r\nr:#fff&quot;&gt;\n&lt;span&gt;=A0&lt;/span&gt;\n\n\n&lt;div&gt;\n  &lt;div&gt;\n\n\n    &lt;div&gt;\n      \n      \n      &lt;=\r\np&gt;Evolution is not how biological neural networks learn. Are there any\nproj=\r\nects (similar in scope/usability to NEAT) that are more faithful to\nbiology=\r\n?&lt;br&gt;\n&lt;br&gt;Richard Gong&lt;br&gt;&lt;br&gt;&lt;br&gt;&lt;/p&gt;&lt;div class=3D&quot;gmail_quote&quot;&gt;----------=\r\n Forwarded message ----------&lt;br&gt;From: &lt;b class=3D&quot;gmail_sendername&quot;&gt;Dave T=\r\nouretzky&lt;/b&gt; &lt;span dir=3D&quot;ltr&quot;&gt;&lt;&lt;a href=3D&quot;mailto:dst@...=\r\n.edu&quot; target=3D&quot;_blank&quot;&gt;dst@...&lt;/a&gt;&gt;&lt;/span&gt;&lt;br&gt;\n\nDate=\r\n: Sat, Nov 28, 2009 at 1:59 AM&lt;br&gt;Subject: Re: AI&lt;br&gt;To: Richard Gong &lt;&lt;=\r\na href=3D&quot;mailto:richardgong@...&quot; target=3D&quot;_blank&quot;&gt;richardgong@gmail=\r\n.com&lt;/a&gt;&gt;&lt;br&gt;&lt;br&gt;&lt;br&gt;&lt;div&gt;&gt; Are there any coding projects similar to =\r\nNEAT, in its generalized&lt;br&gt;\n\n\n&gt; ability, but more like the brain&#39;s =\r\n&quot;live&quot; learning?&lt;br&gt;\n&lt;br&gt;\n&lt;/div&gt;No one knows in detail how learni=\r\nng works in the brain. =A0We don&#39;t know&lt;br&gt;\nhow most things are represe=\r\nnted, or how those representations get&lt;br&gt;\nupdated. =A0All we have right no=\r\nw are highly simplified models at various&lt;br&gt;\nlevels of abstraction, but we=\r\n know that these are inadequate.&lt;br&gt;\n&lt;br&gt;\nDon&#39;t be misled by computer s=\r\ncientists who give simple learning&lt;br&gt;\nmechanisms fancy biological names, l=\r\nike &quot;neural network&quot; or &quot;genetic&lt;br&gt;\nalgorithm&quot;. =A0The=\r\nse are highly simplified and abstract mathematical&lt;br&gt;\nconstructs compared =\r\nto the complicated and messy biological phenomena&lt;br&gt;\nthey are named after.=\r\n =A0It&#39;s like the difference between the hypothetical&lt;br&gt;\ncanonball&#39=\r\n;s simple 1D trajectory in a vacuum, vs. a real world&lt;br&gt;\nknuckleball whose=\r\n spin and trajectory can only be explained using vector&lt;br&gt;\ncalculus and fl=\r\nuid dynamics.&lt;br&gt;\n&lt;br&gt;\nSo to answer your original question: no, we don&#39;=\r\nt have a general purpose&lt;br&gt;\nlearning rule that works like the brain, becau=\r\nse we don&#39;t understand how&lt;br&gt;\nthe brain works.&lt;br&gt;\n&lt;br&gt;\nAnd although b=\r\nrains have very powerful learning algorithms, they also&lt;br&gt;\nhave a lot of b=\r\nuilt-in structure that is present from birth. =A0Most&lt;br&gt;\nmachine learning =\r\nalgorithms start out with zero weights, or initial&lt;br&gt;\nrandom weights, not =\r\nthe incredibly detailed structure produced by our&lt;br&gt;\ngenes through the pro=\r\ncess of fetal development. =A0So don&#39;t think that&lt;br&gt;\nsome simple learn=\r\ning algorithm is going to provide the &quot;magic bullet&quot;&lt;br&gt;\nthat pro=\r\nduces intelligent machines. =A0It&#39;s not going to be that easy. =A0It&lt;br=\r\n&gt;\ntook evolution a long time to come up with the structure of the&lt;br&gt;\nmamma=\r\nlian brain. =A0And it&#39;s going to take us another century or two to&lt;br&gt;\n=\r\nfigure out how it works.&lt;br&gt;\n&lt;div&gt;&lt;div&gt;&lt;/div&gt;&lt;div&gt;&lt;br&gt;\n-- Dr. David S. Tour=\r\netzky&lt;br&gt;\n =A0 Research Professor&lt;br&gt;\n =A0 Computer Science Department &amp=\r\n;&lt;br&gt;\n =A0 =A0 Center for the Neural Basis of Cognition&lt;br&gt;\n =A0 Carnegie M=\r\nellon University&lt;br&gt;\n =A0 Pittsburgh, PA 15213-3891&lt;br&gt;\n =A0 tel. 412-268-7=\r\n561&lt;br&gt;\n&lt;/div&gt;&lt;/div&gt;&lt;/div&gt;&lt;br&gt;\n&lt;p&gt;&lt;/p&gt;\n\n    &lt;/div&gt;\n     \n\n    \n    &lt;div sty=\r\nle=3D&quot;color:#fff;min-height:0&quot;&gt;&lt;/div&gt;\n\n\n&lt;/div&gt;\n\n\n\n  \n\n\n\n\n\n\n&lt;/blockquote&gt;&lt;/d=\r\niv&gt;&lt;br&gt;&lt;br clear=3D&quot;all&quot;&gt;&lt;br&gt;-- &lt;br&gt;...imagine a puddle waking up one morni=\r\nng and thinking, &#39;This is an interesting world I find myself in, an int=\r\neresting hole I find myself in, fits me rather neatly, doesn&#39;t it? In f=\r\nact it fits me staggeringly well, must have been made to have me in it!&#39=\r\n; This is such a powerful idea that as the sun rises in the sky and the air=\r\n heats up and as, gradually, the puddle gets smaller and smaller, it&#39;s =\r\nstill frantically hanging on to the notion that everything&#39;s going to b=\r\ne alright, because this world was meant to have him in it, was built to hav=\r\ne him in it; so the moment he disappears catches him rather by surprise. I =\r\nthink this may be something we need to be on the watch out for.&lt;br&gt;\n&lt;br&gt;-- =\r\nDouglas Adams&lt;br&gt;\n&lt;/div&gt;\n\r\n--0016e652f6b0126d6004797d2f8b--\r\n\n"}}