{"ygPerms":{"resourceCapabilityList":[{"resourceType":"GROUP","capabilities":[{"name":"READ"},{"name":"JOIN"}]},{"resourceType":"PHOTO","capabilities":[]},{"resourceType":"FILE","capabilities":[]},{"resourceType":"MEMBER","capabilities":[]},{"resourceType":"LINK","capabilities":[]},{"resourceType":"CALENDAR","capabilities":[]},{"resourceType":"DATABASE","capabilities":[]},{"resourceType":"POLL","capabilities":[]},{"resourceType":"MESSAGE","capabilities":[{"name":"READ"}]},{"resourceType":"PENDING_MESSAGE","capabilities":[]},{"resourceType":"ATTACHMENTS","capabilities":[{"name":"READ"}]},{"resourceType":"PHOTOMATIC_ALBUMS","capabilities":[]},{"resourceType":"MEMBERSHIP_TYPE","capabilities":[]},{"resourceType":"POST","capabilities":[{"name":"READ"}]},{"resourceType":"PIN","capabilities":[]}],"groupUrl":"groups.yahoo.com","intlCode":"us"},"comscore":"pageview_candidate","ygData":{"userId":54567749,"authorName":"Kenneth Stanley","from":"&quot;Kenneth Stanley&quot; &lt;kstanley@...&gt;","profile":"kenstanley01","replyTo":"LIST","senderId":"2k9DFhJ7pi1ROXsqeBwapk4SXgAJ6XO0mxYZhCENGLwt0-3TDGUIt3yUL9g1Cz8uAzaDYG2ZwqIl8h3ztkmH5jOeRQcGwPdQ-4BZANZmrFKM","spamInfo":{"isSpam":false,"reason":"0"},"subject":"Re: Concentration Game","postDate":"1066285881","msgId":145,"canDelete":false,"contentTrasformed":false,"systemMessage":false,"headers":{"messageIdInHeader":"PGJtbGR2cCtucW1rQGVHcm91cHMuY29tPg==","inReplyToHeader":"PDIwMDMxMDE2MDYyMjM2LjYyMzcxLnFtYWlsQHdlYjIxNDA0Lm1haWwueWFob28uY29tPg=="},"prevInTopic":144,"nextInTopic":146,"prevInTime":144,"nextInTime":146,"topicId":135,"numMessagesInTopic":10,"msgSnippet":"... We have a paper on measuring progress in competitive coevolution that you may find it useful: http://nn.cs.utexas.edu/pub-view.php?RECORD_KEY(Pu ","rawEmail":"Return-Path: &lt;kstanley@...&gt;\r\nX-Sender: kstanley@...\r\nX-Apparently-To: neat@yahoogroups.com\r\nReceived: (qmail 54604 invoked from network); 16 Oct 2003 06:31:22 -0000\r\nReceived: from unknown (66.218.66.217)\n  by m2.grp.scd.yahoo.com with QMQP; 16 Oct 2003 06:31:22 -0000\r\nReceived: from unknown (HELO n10.grp.scd.yahoo.com) (66.218.66.65)\n  by mta2.grp.scd.yahoo.com with SMTP; 16 Oct 2003 06:31:22 -0000\r\nReceived: from [66.218.66.123] by n10.grp.scd.yahoo.com with NNFMP; 16 Oct 2003 06:31:22 -0000\r\nDate: Thu, 16 Oct 2003 06:31:21 -0000\r\nTo: neat@yahoogroups.com\r\nSubject: Re: Concentration Game\r\nMessage-ID: &lt;bmldvp+nqmk@...&gt;\r\nIn-Reply-To: &lt;20031016062236.62371.qmail@...&gt;\r\nUser-Agent: eGroups-EW/0.82\r\nMIME-Version: 1.0\r\nContent-Type: text/plain; charset=ISO-8859-1\r\nContent-Length: 539\r\nX-Mailer: Yahoo Groups Message Poster\r\nFrom: &quot;Kenneth Stanley&quot; &lt;kstanley@...&gt;\r\nX-Yahoo-Group-Post: member; u=54567749\r\nX-Yahoo-Profile: kenstanley01\r\n\r\n&gt; \n&gt; That is an unforeseen problem with co-evolution; you\n&gt; can&#39;t easily tell how they are doing if the evolve\n&gt; together.  I need to add some objective measure\n&gt; because I like to know what&#39;s happening.  I won&#39;t use\n&gt; that for evolution, just for observation.\n&gt; \n&gt; \n\nWe have a paper on measuring progress in competitive\ncoevolution that you may find it useful:\n\nhttp://nn.cs.utexas.edu/pub-view.php?RECORD_KEY(Pu\nbs)=PubID&PubID(Pubs)=113\n\nThis paper describes a way to check for increasing levels of\ndominance in a coevolution run.\n\nken\n\n\n"}}