{"ygPerms":{"resourceCapabilityList":[{"resourceType":"GROUP","capabilities":[{"name":"READ"},{"name":"JOIN"}]},{"resourceType":"PHOTO","capabilities":[]},{"resourceType":"FILE","capabilities":[]},{"resourceType":"MEMBER","capabilities":[]},{"resourceType":"LINK","capabilities":[]},{"resourceType":"CALENDAR","capabilities":[]},{"resourceType":"DATABASE","capabilities":[]},{"resourceType":"POLL","capabilities":[]},{"resourceType":"MESSAGE","capabilities":[{"name":"READ"}]},{"resourceType":"PENDING_MESSAGE","capabilities":[]},{"resourceType":"ATTACHMENTS","capabilities":[{"name":"READ"}]},{"resourceType":"PHOTOMATIC_ALBUMS","capabilities":[]},{"resourceType":"MEMBERSHIP_TYPE","capabilities":[]},{"resourceType":"POST","capabilities":[{"name":"READ"}]},{"resourceType":"PIN","capabilities":[]}],"groupUrl":"groups.yahoo.com","intlCode":"us"},"comscore":"pageview_candidate","ygData":{"userId":150579383,"authorName":"Sidhant Dash","from":"Sidhant Dash &lt;sidhantdash@...&gt;","profile":"sidhantdash","replyTo":"LIST","senderId":"2wo9ZYI0a89mPIMk6jJnstczloP0VWmJySxILXDRAZy35YRP_tLYVt1vzuuGV1RDIHQ12C1bbPKUcEMewBa6Rh3vA5eIcpp5L75s","spamInfo":{"isSpam":false,"reason":"0"},"subject":"Re: [neat] Recommended Neural Network Book?","postDate":"1166116542","msgId":2893,"canDelete":false,"contentTrasformed":false,"systemMessage":false,"headers":{"messageIdInHeader":"PDM4MjgzNS41NDYyMi5xbUB3ZWI2MjUwNy5tYWlsLnJlMS55YWhvby5jb20+","inReplyToHeader":"PEMxQTVEMTY0LjE2Qzc3JWpjbHVuZUBtc3UuZWR1Pg=="},"prevInTopic":2892,"nextInTopic":2896,"prevInTime":2892,"nextInTime":2894,"topicId":2886,"numMessagesInTopic":10,"msgSnippet":"Hi, I recommend Neural network recipes in C++ by Timothy Masters. The book does a great job of explaining the mathematical equations. It doesnt assume much","rawEmail":"Return-Path: &lt;sidhantdash@...&gt;\r\nX-Sender: sidhantdash@...\r\nX-Apparently-To: neat@yahoogroups.com\r\nReceived: (qmail 84280 invoked from network); 14 Dec 2006 17:22:34 -0000\r\nReceived: from unknown (66.218.66.167)\n  by m24.grp.scd.yahoo.com with QMQP; 14 Dec 2006 17:22:34 -0000\r\nReceived: from unknown (HELO web62507.mail.re1.yahoo.com) (69.147.75.99)\n  by mta6.grp.scd.yahoo.com with SMTP; 14 Dec 2006 17:22:33 -0000\r\nReceived: (qmail 55151 invoked by uid 60001); 14 Dec 2006 17:15:42 -0000\r\nX-YMail-OSG: 43IHcEcVM1k9nXOxOwu6nosLIgEVTBsoQFoSVjbh\r\nReceived: from [61.1.174.225] by web62507.mail.re1.yahoo.com via HTTP; Thu, 14 Dec 2006 09:15:42 PST\r\nDate: Thu, 14 Dec 2006 09:15:42 -0800 (PST)\r\nTo: neat@yahoogroups.com\r\nIn-Reply-To: &lt;C1A5D164.16C77%jclune@...&gt;\r\nMIME-Version: 1.0\r\nContent-Type: multipart/alternative; boundary=&quot;0-996039343-1166116542=:54622&quot;\r\nContent-Transfer-Encoding: 8bit\r\nMessage-ID: &lt;382835.54622.qm@...&gt;\r\nX-eGroups-Msg-Info: 1:0:0:0\r\nFrom: Sidhant Dash &lt;sidhantdash@...&gt;\r\nSubject: Re: [neat] Recommended Neural Network Book?\r\nX-Yahoo-Group-Post: member; u=150579383; y=0jpklSjGPgLNKncRbJMdc6krdxOXfp604SYFQx9xmm6HNqpf0LY\r\nX-Yahoo-Profile: sidhantdash\r\n\r\n\r\n--0-996039343-1166116542=:54622\r\nContent-Type: text/plain; charset=iso-8859-1\r\nContent-Transfer-Encoding: 8bit\r\n\r\nHi,\n   \n  I recommend &quot;Neural network recipes in C++&quot; by Timothy Masters. The book does a great job of explaining the mathematical equations. It doesnt assume much mathematical maturity, and it also features C++ code to get your neural net up and running. I enjoyed the book. The author gives a lot of useful references and doesnt clutter the text with hundreds of scary equations. You might just take a look at it. \n   \n  Best of luck,\n  Sidhant\n  \n\nJeff Clune &lt;jclune@...&gt; wrote:\n          Hello all-\n\nI am seeking a recommendation for the equivalent of a neural networks for\ndummies book. I have been doing grad research in evolutionary computation\nfor three and a half years now at MSU on the Avida system. I have worked\nwith alife and GAs but have not yet done any real work in neural nets. I\nwould like to use generative representations (e.g. L-systems) to evolve\nneural nets for my dissertation, however, so I need to ramp up on neural\nnets. \n\nFor the next three weeks I will be in Africa and would like to use any free\ntime there to learn as much as I can about neural nets. Is there any book\nthat you recommend I take? I won&#39;t have nearly any internet access, and will\noften not have my computer, so it would be good if the book does not require\neither of those. \n\nI also think better in sentences than equations, so a book that emphasizes\nmore of an intuitive logical explanation rather than mathematical\nformulation (when possible) would be ideal.\n\nAnd, of course, I have put off buying this to the last second so I don&#39;t\nhave time to order it online...but do have a Borders nearby and the many\nUniversity book shops.\n\nGiven all those qualifications, I&#39;m probably out of luck. But I figured if\nthere was something good out there this group would know of it.\n\nAny recommendations you have would be much appreciated.\n\nCheers,\nJeff Clune\n\nDigital Evolution Lab\njclune@...\n517.214.1060 (cell)\n\n\n\n         \n\n\nFear is only as deep as the mind allows. \n--Japanese proverb \n\nMy blog   \n\n \n---------------------------------\nNeed a quick answer? Get one in minutes from people who know. Ask your question on Yahoo! Answers.\r\n--0-996039343-1166116542=:54622\r\nContent-Type: text/html; charset=iso-8859-1\r\nContent-Transfer-Encoding: 8bit\r\n\r\n&lt;div&gt;Hi,&lt;/div&gt;  &lt;div&gt;&nbsp;&lt;/div&gt;  &lt;div&gt;I recommend &quot;Neural network recipes in C++&quot; by Timothy Masters. The book does a great job of explaining the mathematical equations. It doesnt assume much mathematical maturity, and&nbsp;it also features C++ code to get your neural net up and running. I enjoyed the book. The author gives a lot of useful references and doesnt clutter the text with&nbsp;hundreds of scary equations. You might just take a look at it. &lt;/div&gt;  &lt;div&gt;&nbsp;&lt;/div&gt;  &lt;div&gt;Best of luck,&lt;/div&gt;  &lt;div&gt;Sidhant&lt;/div&gt;  &lt;div&gt;&lt;BR&gt;&lt;BR&gt;&lt;B&gt;&lt;I&gt;Jeff Clune &lt;jclune@...&gt;&lt;/I&gt;&lt;/B&gt; wrote:&lt;/div&gt;  &lt;BLOCKQUOTE class=replbq style=&quot;PADDING-LEFT: 5px; MARGIN-LEFT: 5px; BORDER-LEFT: #1010ff 2px solid&quot;&gt;&lt;!-- Network content --&gt;  &lt;DIV id=ygrp-text&gt;  &lt;div&gt;Hello all-&lt;BR&gt;&lt;BR&gt;I am seeking a recommendation for the equivalent of a neural networks for&lt;BR&gt;dummies book. I have been doing grad research in evolutionary computation&lt;BR&gt;for three and a half years now at MSU on the Avida system. I have worked&lt;BR&gt;with alife and GAs but have not yet done any real work in neural nets. I&lt;BR&gt;would like to use generative representations (e.g. L-systems) to evolve&lt;BR&gt;neural nets for my dissertation, however, so I need to ramp up on neural&lt;BR&gt;nets. &lt;BR&gt;&lt;BR&gt;For the next three weeks I will be in Africa and would like to use any free&lt;BR&gt;time there to learn as much as I can about neural nets. Is there any book&lt;BR&gt;that you recommend I take? I won&#39;t have nearly any internet access, and will&lt;BR&gt;often not have my computer, so it would be good if the book does not require&lt;BR&gt;either of those. &lt;BR&gt;&lt;BR&gt;I also think better in sentences than equations, so a book that emphasizes&lt;BR&gt;more of an\n intuitive logical explanation rather than mathematical&lt;BR&gt;formulation (when possible) would be ideal.&lt;BR&gt;&lt;BR&gt;And, of course, I have put off buying this to the last second so I don&#39;t&lt;BR&gt;have time to order it online...but do have a Borders nearby and the many&lt;BR&gt;University book shops.&lt;BR&gt;&lt;BR&gt;Given all those qualifications, I&#39;m probably out of luck. But I figured if&lt;BR&gt;there was something good out there this group would know of it.&lt;BR&gt;&lt;BR&gt;Any recommendations you have would be much appreciated.&lt;BR&gt;&lt;BR&gt;Cheers,&lt;BR&gt;Jeff Clune&lt;BR&gt;&lt;BR&gt;Digital Evolution Lab&lt;BR&gt;&lt;A href=&quot;mailto:jclune%40msu.edu&quot;&gt;jclune@...&lt;/A&gt;&lt;BR&gt;517.214.1060 (cell)&lt;BR&gt;&lt;BR&gt;&lt;/div&gt;&lt;/DIV&gt;&lt;!--End group email --&gt;&lt;/BLOCKQUOTE&gt;&lt;BR&gt;&lt;BR&gt;&lt;BR&gt;&lt;DIV&gt;Fear is only as deep as the mind allows. &lt;BR&gt;--Japanese proverb &lt;BR&gt;&lt;BR&gt;&lt;A href=&quot;http://sidhantdash.blogspot.com&quot;&gt;My blog&lt;/A&gt;&nbsp;&nbsp; &lt;/DIV&gt;&lt;p&gt;&#32;\n\n&lt;hr size=1&gt;Need a quick answer? Get one in minutes from people who know. Ask your question on\n &lt;a href=&quot;http://answers.yahoo.com/;_ylc=X3oDMTFvbGNhMGE3BF9TAzM5NjU0NTEwOARfcwMzOTY1NDUxMDMEc2VjA21haWxfdGFnbGluZQRzbGsDbWFpbF90YWcx&quot;&gt;Yahoo! Answers&lt;/a&gt;.\r\n--0-996039343-1166116542=:54622--\r\n\n"}}